kilonova_heating_rate/__init__.py
kilonova_heating_rate-0.1.0.dist-info/LICENSE.rst
kilonova_heating_rate-0.1.0.dist-info/LICENSE
kilonova_heating_rate-0.1.0.dist-info/WHEEL
kilonova_heating_rate-0.1.0.dist-info/METADATA
kilonova_heating_rate-0.1.0.dist-info/RECORD
