Metadata-Version: 2.1
Name: kilonova-heating-rate
Version: 0.1.0
Summary: Kilonova light curves from Hotokezaka & Nakar 2019
License: BSD-3-Clause
Author: Bas Dorsman
Author-email: bas.dorsman@student.uva.nl
Requires-Python: >=3.7,<4.0
Classifier: Development Status :: 3 - Alpha
Classifier: Intended Audience :: Science/Research
Classifier: License :: OSI Approved :: BSD License
Classifier: Programming Language :: Python :: 3
Classifier: Programming Language :: Python :: 3 :: Only
Classifier: Programming Language :: Python :: 3.7
Classifier: Programming Language :: Python :: 3.8
Classifier: Programming Language :: Python :: 3.9
Classifier: Topic :: Scientific/Engineering :: Astronomy
Requires-Dist: astropy
Requires-Dist: numpy
Requires-Dist: scipy
